<XMLConfigSettings>
	<FILEINFO type="SourceInfo" descr="Editor information for file NPCZombie.pwn" ts="30049528"/>
	<Document position="(4,351)" top="307">
		<Collapsed count="102">
			<Scope idx="2"/>
			<Scope idx="3"/>
			<Scope idx="4"/>
			<Scope idx="5"/>
			<Scope idx="6"/>
			<Scope idx="12"/>
			<Scope idx="20"/>
			<Scope idx="22"/>
			<Scope idx="26"/>
			<Scope idx="46"/>
			<Scope idx="48"/>
			<Scope idx="50"/>
			<Scope idx="58"/>
			<Scope idx="59"/>
			<Scope idx="62"/>
			<Scope idx="63"/>
			<Scope idx="64"/>
			<Scope idx="65"/>
			<Scope idx="67"/>
			<Scope idx="70"/>
			<Scope idx="71"/>
			<Scope idx="72"/>
			<Scope idx="74"/>
			<Scope idx="78"/>
			<Scope idx="79"/>
			<Scope idx="82"/>
			<Scope idx="85"/>
			<Scope idx="86"/>
			<Scope idx="87"/>
			<Scope idx="88"/>
			<Scope idx="89"/>
			<Scope idx="92"/>
			<Scope idx="98"/>
		</Collapsed>
	</Document>
</XMLConfigSettings>
