<XMLConfigSettings>
	<FILEINFO type="SourceInfo" descr="Editor information for file football.pwn" ts="30088090"/>
	<Document position="(0,1490)">
		<Collapsed count="406">
			<Scope idx="0"/>
			<Scope idx="213"/>
			<Scope idx="214"/>
			<Scope idx="215"/>
			<Scope idx="216"/>
			<Scope idx="217"/>
			<Scope idx="218"/>
			<Scope idx="219"/>
			<Scope idx="220"/>
			<Scope idx="221"/>
			<Scope idx="222"/>
			<Scope idx="223"/>
			<Scope idx="224"/>
			<Scope idx="225"/>
			<Scope idx="226"/>
			<Scope idx="227"/>
			<Scope idx="228"/>
			<Scope idx="229"/>
			<Scope idx="230"/>
			<Scope idx="231"/>
			<Scope idx="232"/>
			<Scope idx="233"/>
			<Scope idx="234"/>
			<Scope idx="235"/>
			<Scope idx="236"/>
			<Scope idx="238"/>
			<Scope idx="240"/>
			<Scope idx="241"/>
			<Scope idx="242"/>
			<Scope idx="243"/>
			<Scope idx="244"/>
			<Scope idx="245"/>
			<Scope idx="246"/>
			<Scope idx="247"/>
			<Scope idx="248"/>
			<Scope idx="249"/>
			<Scope idx="250"/>
			<Scope idx="252"/>
			<Scope idx="254"/>
			<Scope idx="255"/>
			<Scope idx="257"/>
			<Scope idx="258"/>
			<Scope idx="259"/>
			<Scope idx="260"/>
			<Scope idx="261"/>
			<Scope idx="265"/>
			<Scope idx="267"/>
			<Scope idx="268"/>
			<Scope idx="269"/>
			<Scope idx="270"/>
			<Scope idx="271"/>
			<Scope idx="273"/>
			<Scope idx="274"/>
			<Scope idx="275"/>
			<Scope idx="276"/>
			<Scope idx="277"/>
			<Scope idx="278"/>
			<Scope idx="279"/>
			<Scope idx="280"/>
			<Scope idx="281"/>
			<Scope idx="282"/>
			<Scope idx="283"/>
			<Scope idx="284"/>
			<Scope idx="285"/>
			<Scope idx="286"/>
			<Scope idx="287"/>
			<Scope idx="288"/>
			<Scope idx="289"/>
			<Scope idx="290"/>
			<Scope idx="291"/>
			<Scope idx="292"/>
			<Scope idx="293"/>
			<Scope idx="294"/>
			<Scope idx="295"/>
			<Scope idx="296"/>
			<Scope idx="297"/>
			<Scope idx="298"/>
			<Scope idx="299"/>
			<Scope idx="300"/>
			<Scope idx="301"/>
			<Scope idx="302"/>
			<Scope idx="303"/>
			<Scope idx="306"/>
			<Scope idx="307"/>
			<Scope idx="308"/>
			<Scope idx="309"/>
			<Scope idx="310"/>
			<Scope idx="311"/>
			<Scope idx="312"/>
			<Scope idx="317"/>
			<Scope idx="318"/>
			<Scope idx="319"/>
			<Scope idx="320"/>
			<Scope idx="321"/>
			<Scope idx="322"/>
			<Scope idx="323"/>
			<Scope idx="324"/>
			<Scope idx="325"/>
			<Scope idx="326"/>
			<Scope idx="327"/>
			<Scope idx="328"/>
			<Scope idx="329"/>
			<Scope idx="330"/>
			<Scope idx="331"/>
			<Scope idx="332"/>
			<Scope idx="333"/>
			<Scope idx="334"/>
			<Scope idx="335"/>
			<Scope idx="336"/>
			<Scope idx="337"/>
			<Scope idx="338"/>
			<Scope idx="339"/>
			<Scope idx="340"/>
			<Scope idx="341"/>
			<Scope idx="342"/>
			<Scope idx="343"/>
			<Scope idx="344"/>
			<Scope idx="345"/>
			<Scope idx="346"/>
			<Scope idx="347"/>
			<Scope idx="348"/>
			<Scope idx="349"/>
			<Scope idx="350"/>
			<Scope idx="351"/>
			<Scope idx="352"/>
			<Scope idx="353"/>
			<Scope idx="354"/>
			<Scope idx="355"/>
			<Scope idx="356"/>
			<Scope idx="357"/>
			<Scope idx="358"/>
			<Scope idx="359"/>
			<Scope idx="360"/>
			<Scope idx="361"/>
			<Scope idx="362"/>
			<Scope idx="363"/>
			<Scope idx="364"/>
			<Scope idx="365"/>
			<Scope idx="366"/>
			<Scope idx="375"/>
			<Scope idx="378"/>
			<Scope idx="380"/>
			<Scope idx="381"/>
			<Scope idx="382"/>
			<Scope idx="383"/>
			<Scope idx="388"/>
			<Scope idx="389"/>
			<Scope idx="390"/>
			<Scope idx="391"/>
			<Scope idx="392"/>
			<Scope idx="393"/>
			<Scope idx="394"/>
			<Scope idx="395"/>
			<Scope idx="396"/>
			<Scope idx="397"/>
			<Scope idx="398"/>
			<Scope idx="402"/>
			<Scope idx="404"/>
		</Collapsed>
	</Document>
</XMLConfigSettings>
